octo_pipeline_python/backends/git/__init__.py
octo_pipeline_python/backends/git/git_backend.py
octo_pipeline_python/backends/git/actions/__init__.py
octo_pipeline_python/backends/git/actions/git_mirror.py
octo_pipeline_python/backends/git/actions/git_source.py
octo_pipeline_python/backends/git/models/__init__.py
octo_pipeline_python/backends/git/models/git_backend_model.py
octo_pipeline_backend_git_python-1.3.2.dist-info/LICENSE.txt
octo_pipeline_backend_git_python-1.3.2.dist-info/METADATA
octo_pipeline_backend_git_python-1.3.2.dist-info/README.md
octo_pipeline_backend_git_python-1.3.2.dist-info/WHEEL
octo_pipeline_backend_git_python-1.3.2.dist-info/top_level.txt
octo_pipeline_backend_git_python-1.3.2.dist-info/RECORD
